{
    "metadata": {
        "creation_time": "Fri Aug 29 15:40:28 2025",
        "monitored_folder": "sensitive-data/",
        "baseline_version": 1.0,
        "algorithm": "sha256"
    },
    "files": {
        "passwords.txt": {
            "file_name": "passwords.txt",
            "hash": "349abe1272178917136372f667b13753e2c775bbe39112118420b7697749c97b",
            "permissions": "-rw-rw-r--",
            "creation_time": "Thu Aug 28 18:53:23 2025",
            "last_time_accessed": "Thu Aug 28 21:02:53 2025",
            "last_time_modified": "Thu Aug 28 18:44:11 2025",
            "owner": "vinas",
            "group": "vinas"
        },
        "test.txt": {
            "file_name": "test.txt",
            "hash": "55f8718109829bf506b09d8af615b9f107a266e19f7a311039d1035f180b22d4",
            "permissions": "-rw-rw-r--",
            "creation_time": "Fri Aug 29 16:04:52 2025",
            "last_time_accessed": "Fri Aug 29 16:04:58 2025",
            "last_time_modified": "Fri Aug 29 16:04:52 2025",
            "owner": "vinas",
            "group": "vinas"
        },
        "backup001.bkp": {
            "file_name": "backup001.bkp",
            "hash": "e3b0c44298fc1c149afbf4c8996fb92427ae41e4649b934ca495991b7852b855",
            "a": "-rw-r--r--",
            "creation_time": "Sat Aug 30 15:45:44 2025",
            "last_time_accessed": "Sat Aug 30 15:45:44 2025",
            "last_time_modified": "Sat Aug 30 15:45:44 2025",
            "owner": "vinas",
            "group": "vinas"
        },
        "usernames.txt": {
            "file_name": "usernames.txt",
            "hash": "3fde87644df6aab6e3ba2c7ee3c21ae5643a37e0de186b1294d5fe30e7cc89e0",
            "permissions": "-rw-r--r--",
            "creation_time": "Fri Sep  5 17:23:16 2025",
            "last_time_accessed": "Fri Sep  5 17:23:16 2025",
            "last_time_modified": "Fri Sep  5 17:23:16 2025",
            "owner": "vinas",
            "group": "vinas"
        },
        "only-admins.txt": {
            "file_name": "only-admins.txt",
            "hash": "9b9abaa31bcb85cf8b4fbf48a49a832109cd5a1139116b6ea4ea0791f527702b",
            "permissions": "-rw-r--r--",
            "creation_time": "Fri Sep  5 17:55:49 2025",
            "last_time_accessed": "Fri Sep  5 17:55:28 2025",
            "last_time_modified": "Fri Sep  5 17:55:49 2025",
            "owner": "vinas",
            "group": "administrators"
        },
        "fantasma.txt": {
            "file_name": "fantasma.txt",
            "hash": "eb91bbad021bfa1a17bb8ea9d1804ae167f058e9cae43e8828b174f3ee16b377",
            "permissions": "-rw-rw-r--",
            "creation_time": "Thu Sep 11 18:41:57 2025",
            "last_time_accessed": "Thu Sep 11 18:41:58 2025",
            "last_time_modified": "Thu Sep 11 18:41:57 2025",
            "owner": "vinas",
            "group": "vinas"
        }
    }
}